llama_index/storage/kvstore/postgres/__init__.py
llama_index/storage/kvstore/postgres/base.py
llama_index_storage_kvstore_postgres-0.4.3.dist-info/METADATA
llama_index_storage_kvstore_postgres-0.4.3.dist-info/WHEEL
llama_index_storage_kvstore_postgres-0.4.3.dist-info/licenses/LICENSE
llama_index_storage_kvstore_postgres-0.4.3.dist-info/RECORD
